pic2text
