Metadata-Version: 1.1
Name: pic2text
Version: 0.8
Summary: A small tool that converts photos to semi-readable/viewable strings and then pastes them in the cmd-line or outputs a txt file
Home-page: https://github.com/STJudd109/pic2text
Author: Spencer Judd
Author-email: spencerjfam@gmail.com
License: UNKNOWN
Download-URL: https://github.com/STJudd109/pic2text/archive/v0.8.tar.gz
Keywords: picture,commandline,silly
Platform: UNKNOWN
